{
  "todoItems" : {
    "-KgIKiH8e7IYHZplrMVE" : {
      "done" : false,
      "task" : "X"
    },
    "-KgIKiL0tVEt50CPmVfN" : {
      "done" : false,
      "task" : "X"
    },
    "-KgIKiP6uIlQcTd8DKJ8" : {
      "done" : false,
      "task" : "X"
    },
    "-KgIKiT2tZDxCx4IV3NY" : {
      "done" : false,
      "task" : "X"
    },
    "-KgIKiWrLOFZYJa2wIl4" : {
      "done" : false,
      "task" : "X"
    },
    "-KgIKiahNszu_56aPLSE" : {
      "done" : false,
      "task" : "X"
    },
    "-KgIKifktLBa5IonNHy7" : {
      "done" : false,
      "task" : "X"
    },
    "-KgIKil-T_8nyJUkSAAv" : {
      "done" : false,
      "task" : "X"
    },
    "-KgIKipHXdh9dd-VdN1E" : {
      "done" : false,
      "task" : "X"
    },
    "-KgIKitNabgN7YzilWgi" : {
      "done" : false,
      "task" : "X"
    },
    "-KgIKo2LIsIs90I3UiMM" : {
      "done" : false,
      "task" : "Z"
    },
    "-KgIKo7qtDRVA8CujBbE" : {
      "done" : false,
      "task" : "Z"
    },
    "-KgIKoCfN1J6U7Q11Ojv" : {
      "done" : false,
      "task" : "Z"
    },
    "-KgIKoHLojv9VRrRGNZ6" : {
      "done" : false,
      "task" : "Z"
    },
    "-KgIKoMNqtkbRJubHSfk" : {
      "done" : false,
      "task" : "Z"
    },
    "-KgIKoR5wpndkuP-cgwm" : {
      "done" : false,
      "task" : "Z"
    },
    "-KgIKoWQAwLoZCVMRXCm" : {
      "done" : false,
      "task" : "Z"
    },
    "-KgIKoa8ib5nBZMiSIRo" : {
      "done" : false,
      "task" : "Z"
    },
    "-KgIKoecTcMjxsRE_omA" : {
      "done" : false,
      "task" : "Z"
    },
    "-KgIKojoL4j_FSJ2YgCr" : {
      "done" : false,
      "task" : "Z"
    },
    "-KgIKooMFqqqEVzXAgn_" : {
      "done" : false,
      "task" : "Z"
    },
    "-KgIKot5pUod-c4gog2r" : {
      "done" : false,
      "task" : "Z"
    },
    "-KgIKoy5TkBtDhIokX4Y" : {
      "done" : false,
      "task" : "Z"
    },
    "-KgIKp2MVQQlA-vCMzzb" : {
      "done" : false,
      "task" : "Z"
    },
    "-KgIKp7Izn7gliQO_9SY" : {
      "done" : false,
      "task" : "Z"
    },
    "-KgIKpDBqGzKdhlS6YjL" : {
      "done" : false,
      "task" : "Z"
    },
    "-KgIKpKnWSEMNYZHgxyt" : {
      "done" : false,
      "task" : "Z"
    },
    "-KgIKpQPioh9_kpgfnIw" : {
      "done" : false,
      "task" : "Z"
    },
    "-KgIKpVt9qK9TaeMCzD0" : {
      "done" : false,
      "task" : "Z"
    },
    "-KgIKpavr0LdWNc6QM6t" : {
      "done" : false,
      "task" : "Z"
    },
    "-KgIKr4vg1OaFE2CF4QK" : {
      "done" : false,
      "task" : "Y"
    },
    "-KgIKrBu305Tcku3kKEw" : {
      "done" : false,
      "task" : "Y"
    },
    "-KgIKrHjW7S9LAlH42sf" : {
      "done" : false,
      "task" : "Y"
    },
    "-KgIKrNxVPqUEoq9fspP" : {
      "done" : false,
      "task" : "Y"
    },
    "-KgIKrTt2pfvSts8x-GY" : {
      "done" : false,
      "task" : "Y"
    },
    "-KgIKr_6YVDAkkdMwvLD" : {
      "done" : false,
      "task" : "Y"
    },
    "-KgIKrfJaqXkXPfpI-Ez" : {
      "done" : false,
      "task" : "Y"
    },
    "-KgIKrl7MsBi-TmigT41" : {
      "done" : false,
      "task" : "Y"
    },
    "-KgIKrrYJwOA1ueBxe45" : {
      "done" : false,
      "task" : "Y"
    },
    "-KgIKry8FNXz5UkdKAh0" : {
      "done" : false,
      "task" : "Y"
    },
    "-KgIKs32r-VW36GIDcqf" : {
      "done" : false,
      "task" : "Y"
    },
    "-KgIKs9IA1473ozJmS5W" : {
      "done" : false,
      "task" : "Y"
    },
    "-KgIKsFFzUIgqsullroI" : {
      "done" : false,
      "task" : "Y"
    },
    "-KgIKsLMDsfUS4w1hZCf" : {
      "done" : false,
      "task" : "Y"
    },
    "-KgIKsRHKi6UT9jGRZPU" : {
      "done" : false,
      "task" : "Y"
    },
    "-KgIKsX5v5EXw6W6poKY" : {
      "done" : false,
      "task" : "Y"
    },
    "-KgIKsdJ4D1H8fJ6hqJB" : {
      "done" : false,
      "task" : "Y"
    },
    "-KgIKsj9sgowUyfK_KDW" : {
      "done" : false,
      "task" : "Y"
    },
    "-KgIKspIEEnWMdT3Jgba" : {
      "done" : false,
      "task" : "Y"
    },
    "-KgIKsvE9iveoK7bV-CQ" : {
      "done" : false,
      "task" : "Y"
    },
    "-KgIKuxYwqSverNbVmRb" : {
      "done" : false,
      "task" : "A"
    },
    "-KgIKv6MUgMQx3fRiz0g" : {
      "done" : false,
      "task" : "A"
    },
    "-KgIKvD09WkksF-OwIRF" : {
      "done" : false,
      "task" : "A"
    },
    "-KgIKvJ_ZCdZf9HYKjPE" : {
      "done" : false,
      "task" : "A"
    },
    "-KgIKvPlRtmtJ5O7w0_W" : {
      "done" : false,
      "task" : "A"
    },
    "-KgIKvW-QQqMzyPEr8k3" : {
      "done" : false,
      "task" : "A"
    },
    "-KgIKvbGjeIAxRlDtwjp" : {
      "done" : false,
      "task" : "A"
    },
    "-KgIKvhXdU150jlWJg7O" : {
      "done" : false,
      "task" : "A"
    },
    "-KgIKvnwtfc5vx4G4YfG" : {
      "done" : false,
      "task" : "A"
    },
    "-KgIKvuPfzXp33FtEo0A" : {
      "done" : false,
      "task" : "A"
    },
    "-KgIKw-KrUMdWCQJmwUG" : {
      "done" : false,
      "task" : "A"
    },
    "-KgIKw6A71jkkAUk2DY6" : {
      "done" : false,
      "task" : "A"
    },
    "-KgIKwCimMSq4Tw5ND_p" : {
      "done" : false,
      "task" : "A"
    },
    "-KgIKwJ5ED-XWee2W49I" : {
      "done" : false,
      "task" : "A"
    },
    "-KgIKwPQp0Auns-e45Wl" : {
      "done" : false,
      "task" : "A"
    },
    "-KgIKwVYG2TlxEBeyvG_" : {
      "done" : false,
      "task" : "A"
    },
    "-KgIKwcMTvgmRQbS59eh" : {
      "done" : false,
      "task" : "A"
    },
    "-KgIKwjJuVlPah9ayK-J" : {
      "done" : false,
      "task" : "A"
    },
    "-KgIKwpq_rhT7rprANak" : {
      "done" : false,
      "task" : "A"
    },
    "-KgIKwx4aS5Q03n9kDFC" : {
      "done" : false,
      "task" : "A"
    },
    "-KgIKxhij4RGfgh2VxzO" : {
      "done" : false,
      "task" : "N"
    },
    "-KgIKxotGQ_56sr6eXxm" : {
      "done" : false,
      "task" : "N"
    },
    "-KgIKxvpcBHCQE4YOBHl" : {
      "done" : false,
      "task" : "N"
    },
    "-KgIKy1zKJiC6hxfMCLf" : {
      "done" : false,
      "task" : "N"
    },
    "-KgIKy8aevu5Mv_OEiHM" : {
      "done" : false,
      "task" : "N"
    },
    "-KgIKyFb8RdweRuXS3Cj" : {
      "done" : false,
      "task" : "N"
    },
    "-KgIKyN3TVZG16lwS2C1" : {
      "done" : false,
      "task" : "N"
    },
    "-KgIKyUOm7VtYxr-e_Cx" : {
      "done" : false,
      "task" : "N"
    },
    "-KgIKy_sT0XQRiNcfgvL" : {
      "done" : false,
      "task" : "N"
    },
    "-KgIKyh4VFmWHdl2PmKC" : {
      "done" : false,
      "task" : "N"
    },
    "-KgIKynimtNcfnjC8s3X" : {
      "done" : false,
      "task" : "N"
    },
    "-KgIKyualJnbj4QmKFjC" : {
      "done" : false,
      "task" : "N"
    },
    "-KgIKz4U8hKRc2AuXkeV" : {
      "done" : false,
      "task" : "N"
    },
    "-KgIKzCP85zoxC-qKaUC" : {
      "done" : false,
      "task" : "N"
    },
    "-KgIKzKCbxZvY622UCRT" : {
      "done" : false,
      "task" : "N"
    },
    "-KgIKzQlI6gJlrspchWc" : {
      "done" : false,
      "task" : "N"
    },
    "-KgIKzXIJXyzwBf3-1c-" : {
      "done" : false,
      "task" : "N"
    },
    "-KgIKzc_2q5OOAmNTHGs" : {
      "done" : false,
      "task" : "N"
    },
    "-KgIKzj_HYhZA_JWceML" : {
      "done" : false,
      "task" : "N"
    },
    "-KgIKzq032EoorbxMs4b" : {
      "done" : false,
      "task" : "N"
    }
  }
}
